README.md
blaze/__init__.py
blaze/blaze.cpython-312-x86_64-linux-gnu.so
blaze2d-0.4.3.dist-info/METADATA
blaze2d-0.4.3.dist-info/WHEEL
blaze2d-0.4.3.dist-info/RECORD
