Metadata-Version: 2.4
Name: blaze2d
Version: 0.4.3
Classifier: Development Status :: 4 - Beta
Classifier: Intended Audience :: Science/Research
Classifier: License :: OSI Approved :: MIT License
Classifier: Programming Language :: Python :: 3
Classifier: Programming Language :: Python :: 3.9
Classifier: Programming Language :: Python :: 3.10
Classifier: Programming Language :: Python :: 3.11
Classifier: Programming Language :: Python :: 3.12
Classifier: Programming Language :: Rust
Classifier: Topic :: Scientific/Engineering :: Physics
Classifier: Topic :: Scientific/Engineering
Classifier: Operating System :: POSIX :: Linux
Classifier: Operating System :: MacOS
Classifier: Operating System :: Microsoft :: Windows
Requires-Dist: numpy>=1.20
Requires-Dist: matplotlib>=3.5 ; extra == 'plot'
Requires-Dist: matplotlib>=3.5 ; extra == 'all'
Requires-Dist: pandas>=1.3 ; extra == 'all'
Provides-Extra: plot
Provides-Extra: all
Summary: BLAZE - Band-structure LOBPCG Accelerated Zone Eigensolver for 2D Photonic Crystals
Keywords: photonic-crystals,band-structure,eigensolver,LOBPCG,physics,simulation,computational-physics,materials-science
Author-email: RnLe <rene.marcel.lehner@gmail.com>
License: MIT
Requires-Python: >=3.9
